{
  "4417762": [
    {
      "timestamp": "2026-03-17T19:11:15Z",
      "gpus": [
        {
          "util": 77.0,
          "mem_util": 33.0,
          "mem_used": 89139.0,
          "mem_total": 143771.0
        }
      ]
    },
    {
      "timestamp": "2026-03-17T19:17:06Z",
      "gpus": [
        {
          "util": 93.0,
          "mem_util": 40.0,
          "mem_used": 89139.0,
          "mem_total": 143771.0
        }
      ]
    },
    {
      "timestamp": "2026-03-17T19:22:57Z",
      "gpus": [
        {
          "util": 70.0,
          "mem_util": 30.0,
          "mem_used": 89139.0,
          "mem_total": 143771.0
        }
      ]
    },
    {
      "timestamp": "2026-03-17T19:28:34Z",
      "gpus": [
        {
          "util": 77.0,
          "mem_util": 32.0,
          "mem_used": 89139.0,
          "mem_total": 143771.0
        }
      ]
    },
    {
      "timestamp": "2026-03-17T19:34:07Z",
      "gpus": [
        {
          "util": 98.0,
          "mem_util": 41.0,
          "mem_used": 89139.0,
          "mem_total": 143771.0
        }
      ]
    },
    {
      "timestamp": "2026-03-17T19:39:51Z",
      "gpus": [
        {
          "util": 79.0,
          "mem_util": 34.0,
          "mem_used": 89139.0,
          "mem_total": 143771.0
        }
      ]
    },
    {
      "timestamp": "2026-03-17T19:46:06Z",
      "gpus": [
        {
          "util": 99.0,
          "mem_util": 42.0,
          "mem_used": 89139.0,
          "mem_total": 143771.0
        }
      ]
    },
    {
      "timestamp": "2026-03-17T19:51:38Z",
      "gpus": [
        {
          "util": 96.0,
          "mem_util": 41.0,
          "mem_used": 89139.0,
          "mem_total": 143771.0
        }
      ]
    },
    {
      "timestamp": "2026-03-17T19:57:06Z",
      "gpus": [
        {
          "util": 93.0,
          "mem_util": 40.0,
          "mem_used": 89139.0,
          "mem_total": 143771.0
        }
      ]
    },
    {
      "timestamp": "2026-03-17T20:03:08Z",
      "gpus": [
        {
          "util": 65.0,
          "mem_util": 28.0,
          "mem_used": 89139.0,
          "mem_total": 143771.0
        }
      ]
    },
    {
      "timestamp": "2026-03-17T20:09:01Z",
      "gpus": [
        {
          "util": 95.0,
          "mem_util": 40.0,
          "mem_used": 89139.0,
          "mem_total": 143771.0
        }
      ]
    },
    {
      "timestamp": "2026-03-17T20:15:15Z",
      "gpus": [
        {
          "util": 97.0,
          "mem_util": 41.0,
          "mem_used": 89139.0,
          "mem_total": 143771.0
        }
      ]
    }
  ],
  "4430106": [
    {
      "timestamp": "2026-03-17T19:11:15Z",
      "gpus": [
        {
          "util": 100.0,
          "mem_util": 100.0,
          "mem_used": 9377.0,
          "mem_total": 46068.0
        }
      ]
    },
    {
      "timestamp": "2026-03-17T19:17:06Z",
      "gpus": [
        {
          "util": 98.0,
          "mem_util": 100.0,
          "mem_used": 9377.0,
          "mem_total": 46068.0
        }
      ]
    },
    {
      "timestamp": "2026-03-17T19:22:57Z",
      "gpus": [
        {
          "util": 97.0,
          "mem_util": 100.0,
          "mem_used": 9377.0,
          "mem_total": 46068.0
        }
      ]
    },
    {
      "timestamp": "2026-03-17T19:28:34Z",
      "gpus": [
        {
          "util": 98.0,
          "mem_util": 100.0,
          "mem_used": 9377.0,
          "mem_total": 46068.0
        }
      ]
    },
    {
      "timestamp": "2026-03-17T19:34:07Z",
      "gpus": [
        {
          "util": 98.0,
          "mem_util": 100.0,
          "mem_used": 9377.0,
          "mem_total": 46068.0
        }
      ]
    },
    {
      "timestamp": "2026-03-17T19:39:51Z",
      "gpus": [
        {
          "util": 100.0,
          "mem_util": 100.0,
          "mem_used": 9377.0,
          "mem_total": 46068.0
        }
      ]
    },
    {
      "timestamp": "2026-03-17T19:46:06Z",
      "gpus": [
        {
          "util": 98.0,
          "mem_util": 100.0,
          "mem_used": 9377.0,
          "mem_total": 46068.0
        }
      ]
    },
    {
      "timestamp": "2026-03-17T19:51:38Z",
      "gpus": [
        {
          "util": 100.0,
          "mem_util": 100.0,
          "mem_used": 9377.0,
          "mem_total": 46068.0
        }
      ]
    },
    {
      "timestamp": "2026-03-17T19:57:06Z",
      "gpus": [
        {
          "util": 100.0,
          "mem_util": 100.0,
          "mem_used": 9377.0,
          "mem_total": 46068.0
        }
      ]
    },
    {
      "timestamp": "2026-03-17T20:03:08Z",
      "gpus": [
        {
          "util": 100.0,
          "mem_util": 100.0,
          "mem_used": 9377.0,
          "mem_total": 46068.0
        }
      ]
    },
    {
      "timestamp": "2026-03-17T20:09:01Z",
      "gpus": [
        {
          "util": 100.0,
          "mem_util": 100.0,
          "mem_used": 9377.0,
          "mem_total": 46068.0
        }
      ]
    },
    {
      "timestamp": "2026-03-17T20:15:15Z",
      "gpus": [
        {
          "util": 100.0,
          "mem_util": 100.0,
          "mem_used": 9377.0,
          "mem_total": 46068.0
        }
      ]
    }
  ],
  "4430158": [
    {
      "timestamp": "2026-03-17T19:11:15Z",
      "gpus": [
        {
          "util": 99.0,
          "mem_util": 100.0,
          "mem_used": 26587.0,
          "mem_total": 46068.0
        }
      ]
    },
    {
      "timestamp": "2026-03-17T19:17:06Z",
      "gpus": [
        {
          "util": 100.0,
          "mem_util": 99.0,
          "mem_used": 26587.0,
          "mem_total": 46068.0
        }
      ]
    },
    {
      "timestamp": "2026-03-17T19:22:57Z",
      "gpus": [
        {
          "util": 100.0,
          "mem_util": 100.0,
          "mem_used": 26601.0,
          "mem_total": 46068.0
        }
      ]
    },
    {
      "timestamp": "2026-03-17T19:28:34Z",
      "gpus": [
        {
          "util": 100.0,
          "mem_util": 100.0,
          "mem_used": 26601.0,
          "mem_total": 46068.0
        }
      ]
    },
    {
      "timestamp": "2026-03-17T19:34:07Z",
      "gpus": [
        {
          "util": 100.0,
          "mem_util": 100.0,
          "mem_used": 26601.0,
          "mem_total": 46068.0
        }
      ]
    },
    {
      "timestamp": "2026-03-17T19:39:51Z",
      "gpus": [
        {
          "util": 99.0,
          "mem_util": 100.0,
          "mem_used": 26601.0,
          "mem_total": 46068.0
        }
      ]
    },
    {
      "timestamp": "2026-03-17T19:46:06Z",
      "gpus": [
        {
          "util": 100.0,
          "mem_util": 100.0,
          "mem_used": 26601.0,
          "mem_total": 46068.0
        }
      ]
    },
    {
      "timestamp": "2026-03-17T19:51:38Z",
      "gpus": [
        {
          "util": 100.0,
          "mem_util": 100.0,
          "mem_used": 26601.0,
          "mem_total": 46068.0
        }
      ]
    },
    {
      "timestamp": "2026-03-17T19:57:06Z",
      "gpus": [
        {
          "util": 100.0,
          "mem_util": 100.0,
          "mem_used": 26601.0,
          "mem_total": 46068.0
        }
      ]
    },
    {
      "timestamp": "2026-03-17T20:03:08Z",
      "gpus": [
        {
          "util": 100.0,
          "mem_util": 100.0,
          "mem_used": 26601.0,
          "mem_total": 46068.0
        }
      ]
    },
    {
      "timestamp": "2026-03-17T20:09:01Z",
      "gpus": [
        {
          "util": 100.0,
          "mem_util": 100.0,
          "mem_used": 26601.0,
          "mem_total": 46068.0
        }
      ]
    },
    {
      "timestamp": "2026-03-17T20:15:15Z",
      "gpus": [
        {
          "util": 100.0,
          "mem_util": 100.0,
          "mem_used": 26601.0,
          "mem_total": 46068.0
        }
      ]
    }
  ],
  "4430159": [
    {
      "timestamp": "2026-03-17T19:17:06Z",
      "gpus": [
        {
          "util": 0.0,
          "mem_util": 0.0,
          "mem_used": 3.0,
          "mem_total": 46068.0
        }
      ]
    },
    {
      "timestamp": "2026-03-17T19:22:57Z",
      "gpus": [
        {
          "util": 100.0,
          "mem_util": 100.0,
          "mem_used": 26587.0,
          "mem_total": 46068.0
        }
      ]
    },
    {
      "timestamp": "2026-03-17T19:28:34Z",
      "gpus": [
        {
          "util": 100.0,
          "mem_util": 100.0,
          "mem_used": 26599.0,
          "mem_total": 46068.0
        }
      ]
    },
    {
      "timestamp": "2026-03-17T19:34:07Z",
      "gpus": [
        {
          "util": 100.0,
          "mem_util": 100.0,
          "mem_used": 26601.0,
          "mem_total": 46068.0
        }
      ]
    },
    {
      "timestamp": "2026-03-17T19:39:51Z",
      "gpus": [
        {
          "util": 100.0,
          "mem_util": 99.0,
          "mem_used": 26601.0,
          "mem_total": 46068.0
        }
      ]
    },
    {
      "timestamp": "2026-03-17T19:46:06Z",
      "gpus": [
        {
          "util": 100.0,
          "mem_util": 100.0,
          "mem_used": 26601.0,
          "mem_total": 46068.0
        }
      ]
    },
    {
      "timestamp": "2026-03-17T19:51:38Z",
      "gpus": [
        {
          "util": 100.0,
          "mem_util": 100.0,
          "mem_used": 26601.0,
          "mem_total": 46068.0
        }
      ]
    },
    {
      "timestamp": "2026-03-17T19:57:06Z",
      "gpus": [
        {
          "util": 100.0,
          "mem_util": 100.0,
          "mem_used": 26601.0,
          "mem_total": 46068.0
        }
      ]
    },
    {
      "timestamp": "2026-03-17T20:03:08Z",
      "gpus": [
        {
          "util": 100.0,
          "mem_util": 100.0,
          "mem_used": 26601.0,
          "mem_total": 46068.0
        }
      ]
    },
    {
      "timestamp": "2026-03-17T20:09:01Z",
      "gpus": [
        {
          "util": 98.0,
          "mem_util": 100.0,
          "mem_used": 26601.0,
          "mem_total": 46068.0
        }
      ]
    },
    {
      "timestamp": "2026-03-17T20:15:15Z",
      "gpus": [
        {
          "util": 100.0,
          "mem_util": 100.0,
          "mem_used": 26601.0,
          "mem_total": 46068.0
        }
      ]
    }
  ],
  "4430160": [
    {
      "timestamp": "2026-03-17T19:28:34Z",
      "gpus": [
        {
          "util": 0.0,
          "mem_util": 0.0,
          "mem_used": 3.0,
          "mem_total": 46068.0
        }
      ]
    },
    {
      "timestamp": "2026-03-17T19:34:07Z",
      "gpus": [
        {
          "util": 98.0,
          "mem_util": 97.0,
          "mem_used": 26587.0,
          "mem_total": 46068.0
        }
      ]
    },
    {
      "timestamp": "2026-03-17T19:39:51Z",
      "gpus": [
        {
          "util": 100.0,
          "mem_util": 98.0,
          "mem_used": 26599.0,
          "mem_total": 46068.0
        }
      ]
    },
    {
      "timestamp": "2026-03-17T19:46:06Z",
      "gpus": [
        {
          "util": 100.0,
          "mem_util": 100.0,
          "mem_used": 26601.0,
          "mem_total": 46068.0
        }
      ]
    },
    {
      "timestamp": "2026-03-17T19:51:38Z",
      "gpus": [
        {
          "util": 100.0,
          "mem_util": 98.0,
          "mem_used": 26601.0,
          "mem_total": 46068.0
        }
      ]
    },
    {
      "timestamp": "2026-03-17T19:57:06Z",
      "gpus": [
        {
          "util": 100.0,
          "mem_util": 99.0,
          "mem_used": 26601.0,
          "mem_total": 46068.0
        }
      ]
    },
    {
      "timestamp": "2026-03-17T20:03:08Z",
      "gpus": [
        {
          "util": 100.0,
          "mem_util": 97.0,
          "mem_used": 26601.0,
          "mem_total": 46068.0
        }
      ]
    },
    {
      "timestamp": "2026-03-17T20:09:01Z",
      "gpus": [
        {
          "util": 98.0,
          "mem_util": 99.0,
          "mem_used": 26601.0,
          "mem_total": 46068.0
        }
      ]
    },
    {
      "timestamp": "2026-03-17T20:15:15Z",
      "gpus": [
        {
          "util": 100.0,
          "mem_util": 100.0,
          "mem_used": 26601.0,
          "mem_total": 46068.0
        }
      ]
    }
  ]
}